caafe/__init__.py
caafe/caafe.py
caafe/caafe_evaluate.py
caafe/data.py
caafe/evaluate.py
caafe/feature_extension_baselines.py
caafe/metrics.py
caafe/plotting.py
caafe/preprocessing.py
caafe/run_llm_code.py
caafe/sklearn_wrapper.py
caafe-0.1.6.dist-info/LICENSE.txt
caafe-0.1.6.dist-info/METADATA
caafe-0.1.6.dist-info/WHEEL
caafe-0.1.6.dist-info/top_level.txt
caafe-0.1.6.dist-info/RECORD
