Metadata-Version: 2.1
Name: caafe
Version: 0.1.6
Summary: Context-Aware Automated Feature Engineering (CAAFE) is an automated machine learning tool that uses large language models for feature engineering in tabular datasets. It generates Python code for new features along with explanations for their utility, enhancing interpretability.
Home-page: https://github.com/automl/CAAFE
Author: Noah Hollmann, Samuel Müller, Frank Hutter
Author-email: noah.homa@gmail.com
License: LICENSE.txt
Classifier: Development Status :: 3 - Alpha
Classifier: License :: Free for non-commercial use
Classifier: Programming Language :: Python :: 3.7
Classifier: Programming Language :: Python :: 3.8
Classifier: Programming Language :: Python :: 3.9
Requires-Python: >=3.7
License-File: LICENSE.txt
Requires-Dist: openai
Requires-Dist: kaggle
Requires-Dist: openml (==0.12.0)
Requires-Dist: tabpfn
Provides-Extra: full
Requires-Dist: autofeat ; extra == 'full'
Requires-Dist: featuretools ; extra == 'full'
Requires-Dist: tabpfn[full] ; extra == 'full'
